Metadata-Version: 2.1
Name: commitcollector
Version: 2.0.2
Summary: UNKNOWN
Home-page: UNKNOWN
License: UNKNOWN
Platform: UNKNOWN
